README.rst
setup.cfg
setup.py
milachan/__init__.py
milachan/imageman.py
milachan/manager-pymongo.py
milachan/pqueue.py
milachan/robot9000.py
milachan/squema.py
milachan/tripcode.py
milachan.egg-info/PKG-INFO
milachan.egg-info/SOURCES.txt
milachan.egg-info/dependency_links.txt
milachan.egg-info/top_level.txt