Metadata-Version: 1.1
Name: milachan
Version: 0.3.3
Summary: A minimalistic framework for creating simple ImageBoards
Home-page: https://github.com/LuisAlbizo/milachan
Author: Luis Albizo
Author-email: albizo.luis@gmail.com
License: Creative Commons Attribution-ShareAlike 4.0 International License
Keywords: imageboard,framework,chan,backend,database
Platform: UNKNOWN
Classifier: Development Status :: 3 - Alpha
Classifier: Intended Audience :: Developers
Classifier: Topic :: Software Development :: Build Tools
Classifier: License :: Other/Proprietary License 
Classifier: Programming Language :: Python :: 3
Classifier: Programming Language :: Python :: 3.5
Classifier: Programming Language :: Python :: 3.6
